push_notification/__init__.py
push_notification/settings.py
push_notification/urls.py
push_notification/event/__init__.py
push_notification/event/admin.py
push_notification/event/apps.py
push_notification/event/interfaces.py
push_notification/event/models.py
push_notification/event/serializers.py
push_notification/event/tests.py
push_notification/event/views.py
push_notification/event/management/__init__.py
push_notification/event/management/commands/__init__.py
push_notification/event/management/commands/push_notifications_emitter.py
push_notification/event/migrations/0001_initial.py
push_notification/event/migrations/0002_auto_20200403_1401.py
push_notification/event/migrations/0003_use_model_JSONField.py
push_notification/event/migrations/0004_add_custom_fields.py
push_notification/event/migrations/0005_add_ssl.py
push_notification/event/migrations/0006_add_payload_pattern.py
push_notification/event/migrations/__init__.py
nymcard_push_notification-0.2.22.dist-info/METADATA
nymcard_push_notification-0.2.22.dist-info/WHEEL
nymcard_push_notification-0.2.22.dist-info/top_level.txt
nymcard_push_notification-0.2.22.dist-info/RECORD
