Metadata-Version: 2.4
Name: nymcard-push-notification
Version: 0.2.22
Summary: Nymcard Push Notification
Home-page: 
Author: NymCard BNPL Team
Author-email: hello@nuclearo.com
License: MIT
Keywords: Nymcard,Push Notification
Requires-Dist: aiohttp
Requires-Dist: django
Requires-Dist: djangorestframework
Requires-Dist: asgiref
Dynamic: author
Dynamic: author-email
Dynamic: description
Dynamic: description-content-type
Dynamic: keywords
Dynamic: license
Dynamic: requires-dist
Dynamic: summary
